quapp_qiskit/__init__.py
quapp_qiskit/async_tasks/__init__.py
quapp_qiskit/async_tasks/qiskit_circuit_export_task.py
quapp_qiskit/component/__init__.py
quapp_qiskit/component/backend/__init__.py
quapp_qiskit/component/backend/qiskit_invocation.py
quapp_qiskit/component/backend/qiskit_job_fetching.py
quapp_qiskit/factory/__init__.py
quapp_qiskit/factory/qiskit_device_factory.py
quapp_qiskit/factory/qiskit_handler_factory.py
quapp_qiskit/factory/qiskit_provider_factory.py
quapp_qiskit/handler/__init__.py
quapp_qiskit/handler/invocation_handler.py
quapp_qiskit/handler/job_fetching_handler.py
quapp_qiskit/model/__init__.py
quapp_qiskit/model/device/__init__.py
quapp_qiskit/model/device/ibm_cloud_device.py
quapp_qiskit/model/device/ibm_quantum_device.py
quapp_qiskit/model/device/oqc_cloud_device.py
quapp_qiskit/model/device/qapp_qiskit_device.py
quapp_qiskit/model/device/qiskit_device.py
quapp_qiskit/model/provider/__init__.py
quapp_qiskit/model/provider/ibm_cloud_provider.py
quapp_qiskit/model/provider/ibm_quantum_provider.py
quapp_qiskit/model/provider/oqc_cloud_provider.py
quapp_qiskit/model/provider/qapp_qiskit_provider.py
quapp_qiskit-0.0.12.post1.dist-info/licenses/LICENSE
quapp_qiskit-0.0.12.post1.dist-info/METADATA
quapp_qiskit-0.0.12.post1.dist-info/WHEEL
quapp_qiskit-0.0.12.post1.dist-info/top_level.txt
quapp_qiskit-0.0.12.post1.dist-info/RECORD
