Metadata-Version: 2.4
Name: quapp-qiskit
Version: 0.0.12.post1
Summary: Quapp common library supporting Quapp Platform for Quantum Computing
Author-email: "CITYNOW Co. Ltd. " <corp@citynow.vn>
Project-URL: Homepage, https://citynow.asia/
Keywords: quapp,quapp-qiskit,quantum
Classifier: Programming Language :: Python
Classifier: Programming Language :: Python :: 3
Requires-Python: <3.11,>=3.9
License-File: LICENSE
Requires-Dist: quapp-common==0.0.11.dev7
Requires-Dist: qiskit==0.45.3
Requires-Dist: oqc-qcaas-client==3.7.0
Requires-Dist: qiskit-aer-gpu==0.13.3
Requires-Dist: qiskit-ibm-provider==0.10.0
Requires-Dist: qiskit-ibm-runtime==0.19.1
Provides-Extra: dev
Requires-Dist: black; extra == "dev"
Requires-Dist: bumpver; extra == "dev"
Requires-Dist: isort; extra == "dev"
Requires-Dist: pip-tools; extra == "dev"
Requires-Dist: pytest; extra == "dev"
Dynamic: license-file
